__init__.py
cli.py
control.py
controllers.py
flask_jerry.py
mockapi.py
static.py
utils.py
tomcru_jerry-0.1.6.dist-info/LICENSE
tomcru_jerry-0.1.6.dist-info/METADATA
tomcru_jerry-0.1.6.dist-info/WHEEL
tomcru_jerry-0.1.6.dist-info/top_level.txt
tomcru_jerry-0.1.6.dist-info/RECORD
